4counter/counter.v
module counter(CLK, RST_X, cnt);
  input RST_X, CLK;
  output reg [3:0] cnt;
  always @(posedge CLK)  begin
    if (!RST_X)
      cnt <= 4'h0;
    else
      cnt <= cnt + 4'h1;
  end
endmodule

4counter/counter_test.v
module top();
  reg CLK, RST_X;
  wire [3:0] w_cnt;
  counter counter_instance(CLK, RST_X, w_cnt);

  initial begin
    CLK = 0;
    forever #10 CLK = ~CLK;
  end

  initial begin
    RST_X = 0;
    #30 RST_X = 1;
  end

  initial begin
    #500 $finish();
  end

  always @(posedge CLK) begin
    $write("[%t] counter: %b\n", $time, w_cnt);
  end

  initial begin
      $dumpfile("counter_test.vcd");
      $dumpvars(0, counter_instance);
  end

endmodule

4counter/counter_test.vcd
$date
	Sat May  5 10:23:17 2018
$end
$version
	Icarus Verilog
$end
$timescale
	1s
$end
$scope module top $end
$scope module counter_instance $end
$var wire 1 ! CLK $end
$var wire 1 " RST_X $end
$var reg 4 # cnt [3:0] $end
$upscope $end
$upscope $end
$enddefinitions $end
#0
$dumpvars
bx #
0"
0!
$end
#10
b0 #
1!
#20
0!
#30
b1 #
1!
1"
#40
0!
#50
b10 #
1!
#60
0!
#70
b11 #
1!
#80
0!
#90
b100 #
1!
#100
0!
#110
b101 #
1!
#120
0!
#130
b110 #
1!
#140
0!
#150
b111 #
1!
#160
0!
#170
b1000 #
1!
#180
0!
#190
b1001 #
1!
#200
0!
#210
b1010 #
1!
#220
0!
#230
b1011 #
1!
#240
0!
#250
b1100 #
1!
#260
0!
#270
b1101 #
1!
#280
0!
#290
b1110 #
1!
#300
0!
#310
b1111 #
1!
#320
0!
#330
b0 #
1!
#340
0!
#350
b1 #
1!
#360
0!
#370
b10 #
1!
#380
0!
#390
b11 #
1!
#400
0!
#410
b100 #
1!
#420
0!
#430
b101 #
1!
#440
0!
#450
b110 #
1!
#460
0!
#470
b111 #
1!
#480
0!
#490
b1000 #
1!
