half_adder/ha.v
module half_adder(input wire  A,
                  input wire  B,
                  output wire S,
                  output wire C);
   

   assign S = A ^ B;
   assign C = A & B;
   
      
endmodule

half_adder/test.v
module top();
   reg CLK, RST;
   reg A;
   reg B;
   wire S;
   wire C;

   half_adder ha(A, B, S, C);

   initial begin
      CLK = 0;
      forever #10 CLK = ~CLK;
   end

   initial begin
      RST = 0;
      #30 RST = 1;
   end

   /* give A and B */
   initial begin
      A = 0;
      forever #20 A = ~A;
   end
   initial begin
      B = 0;
      forever #40 B = ~B;
   end

   initial begin
      #500 $finish();
   end

   always @(posedge CLK) begin
      $write("[%t] A=%b B=%b C=%b S=%b\n", $time, A, B, C, S);
   end
   
   initial begin
      $dumpfile("test.vcd");
      $dumpvars(0, ha);
   end

endmodule

half_adder/test.vcd
$date
	Sat May  5 11:25:02 2018
$end
$version
	Icarus Verilog
$end
$timescale
	1s
$end
$scope module top $end
$scope module ha $end
$var wire 1 ! A $end
$var wire 1 " B $end
$var wire 1 # C $end
$var wire 1 $ S $end
$upscope $end
$upscope $end
$enddefinitions $end
#0
$dumpvars
0$
0#
0"
0!
$end
#20
1$
1!
#40
0!
1"
#60
0$
1#
1!
#80
0#
0!
0"
#100
1$
1!
#120
0!
1"
#140
0$
1#
1!
#160
0#
0!
0"
#180
1$
1!
#200
0!
1"
#220
0$
1#
1!
#240
0#
0!
0"
#260
1$
1!
#280
0!
1"
#300
0$
1#
1!
#320
0#
0!
0"
#340
1$
1!
#360
0!
1"
#380
0$
1#
1!
#400
0#
0!
0"
#420
1$
1!
#440
0!
1"
#460
0$
1#
1!
#480
0#
0!
0"
#500
1$
1!
